odoo/addons/mrp_bom_structure_report/README.rst
odoo/addons/mrp_bom_structure_report/__init__.py
odoo/addons/mrp_bom_structure_report/__manifest__.py
odoo/addons/mrp_bom_structure_report/i18n/mrp_bom_structure_report.pot
odoo/addons/mrp_bom_structure_report/readme/CONTRIBUTORS.rst
odoo/addons/mrp_bom_structure_report/readme/DESCRIPTION.rst
odoo/addons/mrp_bom_structure_report/readme/USAGE.rst
odoo/addons/mrp_bom_structure_report/reports/__init__.py
odoo/addons/mrp_bom_structure_report/reports/mrp_report_bom_structure.py
odoo/addons/mrp_bom_structure_report/reports/mrp_report_bom_structure.xml
odoo/addons/mrp_bom_structure_report/reports/mrp_report_views_main.xml
odoo/addons/mrp_bom_structure_report/static/description/icon.png
odoo/addons/mrp_bom_structure_report/static/description/index.html
odoo/addons/mrp_bom_structure_report/static/src/js/mrp_bom_report.js
odoo/addons/mrp_bom_structure_report/static/src/scss/mrp_bom_report.scss
odoo/addons/mrp_bom_structure_report/static/src/xml/mrp.xml
odoo/addons/mrp_bom_structure_report/views/mrp_bom_views.xml
odoo/addons/mrp_bom_structure_report/views/mrp_templates.xml
odoo11_addon_mrp_bom_structure_report-11.0.1.2.0.dist-info/METADATA
odoo11_addon_mrp_bom_structure_report-11.0.1.2.0.dist-info/RECORD
odoo11_addon_mrp_bom_structure_report-11.0.1.2.0.dist-info/WHEEL
odoo11_addon_mrp_bom_structure_report-11.0.1.2.0.dist-info/top_level.txt
