Metadata-Version: 2.1
Name: odoo11-addon-mrp-bom-structure-report
Version: 11.0.1.2.0
Summary: MRP BoM Structure Report
Home-page: https://www.github.com/OCA/manufacture-reporting
Author: Odoo SA, Eficent, Odoo Community Association (OCA)
Author-email: support@odoo-community.org
License: AGPL-3
Platform: UNKNOWN
Classifier: Programming Language :: Python
Classifier: Framework :: Odoo
Classifier: License :: OSI Approved :: GNU Affero General Public License v3
Requires-Python: >=2.7, !=3.0.*, !=3.1.*, !=3.2.*, !=3.3.*, !=3.4.*
Requires-Dist: odoo (<11.1dev,>=11.0a)
